LICENSE
MANIFEST.in
README.md
setup.cfg
setup.py
jupyterlab_kite/__init__.py
jupyterlab_kite/_paths.py
jupyterlab_kite/_version.py
jupyterlab_kite/install.json
jupyterlab_kite.egg-info/PKG-INFO
jupyterlab_kite.egg-info/SOURCES.txt
jupyterlab_kite.egg-info/dependency_links.txt
jupyterlab_kite.egg-info/not-zip-safe
jupyterlab_kite.egg-info/requires.txt
jupyterlab_kite.egg-info/top_level.txt
jupyterlab_kite/labextensions/@kiteco/jupyterlab-kite/package.json
jupyterlab_kite/labextensions/@kiteco/jupyterlab-kite/schemas/@kiteco/jupyterlab-kite/package.json.orig
jupyterlab_kite/labextensions/@kiteco/jupyterlab-kite/static/158.d8e73706d03668b124b2.js
jupyterlab_kite/labextensions/@kiteco/jupyterlab-kite/static/158.d8e73706d03668b124b2.js.LICENSE.txt
jupyterlab_kite/labextensions/@kiteco/jupyterlab-kite/static/219.77a6986458cd6e02bec5.js
jupyterlab_kite/labextensions/@kiteco/jupyterlab-kite/static/249.a2fcc30aeb33da4c9ace.js
jupyterlab_kite/labextensions/@kiteco/jupyterlab-kite/static/290.43cc148a860c782f623b.js
jupyterlab_kite/labextensions/@kiteco/jupyterlab-kite/static/290.43cc148a860c782f623b.js.LICENSE.txt
jupyterlab_kite/labextensions/@kiteco/jupyterlab-kite/static/732.d2b5e17c1a5bdff76f2f.js
jupyterlab_kite/labextensions/@kiteco/jupyterlab-kite/static/732.d2b5e17c1a5bdff76f2f.js.LICENSE.txt
jupyterlab_kite/labextensions/@kiteco/jupyterlab-kite/static/736.46132cbc0a7e8a7a9ad7.js
jupyterlab_kite/labextensions/@kiteco/jupyterlab-kite/static/907.2614bdfb3d177639b4b0.js
jupyterlab_kite/labextensions/@kiteco/jupyterlab-kite/static/jupyter-lsp-connection.0d2c4858e20e8454ae0e.js
jupyterlab_kite/labextensions/@kiteco/jupyterlab-kite/static/remoteEntry.89de933cbecc57badb36.js
jupyterlab_kite/labextensions/@kiteco/jupyterlab-kite/static/style.js